templafy/AGENTS.md
templafy/__init__.py
templafy/_version.py
templafy/client.py
templafy/errors.py
templafy/types.py
templafy/api/__init__.py
templafy/api/data_source_fields/__init__.py
templafy/api/data_source_fields/delete_data_sources_data_source_id_fields_field_id.py
templafy/api/data_source_fields/get_data_sources_data_source_id_fields_field_id.py
templafy/api/data_source_fields/patch_data_sources_data_source_id_fields_field_id.py
templafy/api/data_source_fields/post_data_sources_data_source_id_fields.py
templafy/api/data_source_item_fields/__init__.py
templafy/api/data_source_item_fields/delete_data_sources_data_source_id_items_item_id_fields_field_id.py
templafy/api/data_source_item_fields/put_data_sources_data_source_id_items_item_id_fields_field_id.py
templafy/api/data_source_items/__init__.py
templafy/api/data_source_items/delete_data_sources_data_source_id_items_item_id.py
templafy/api/data_source_items/get_data_sources_data_source_id_items.py
templafy/api/data_source_items/get_data_sources_data_source_id_items_item_id.py
templafy/api/data_source_items/patch_data_sources_data_source_id_items_item_id.py
templafy/api/data_source_items/post_data_sources_data_source_id_items.py
templafy/api/data_sources/__init__.py
templafy/api/data_sources/delete_data_sources_id.py
templafy/api/data_sources/get_data_sources.py
templafy/api/data_sources/get_data_sources_id.py
templafy/api/data_sources/patch_data_sources_id.py
templafy/api/data_sources/post_data_sources.py
templafy/api/documents/__init__.py
templafy/api/documents/delete_libraries_space_id_documents_assets_asset_id.py
templafy/api/documents/get_libraries_space_id_documents_assets_asset_id.py
templafy/api/documents/get_libraries_space_id_documents_folders_folder_id_assets.py
templafy/api/documents/patch_libraries_space_id_documents_assets_asset_id.py
templafy/api/documents/post_libraries_space_id_documents_assets_asset_id_generate.py
templafy-2.0.1.dist-info/METADATA
templafy-2.0.1.dist-info/WHEEL
templafy-2.0.1.dist-info/licenses/LICENSE
templafy-2.0.1.dist-info/RECORD
