Metadata-Version: 2.4
Name: templafy
Version: 2.0.1
Summary: A Python client for the Templafy API using openapi-python-client.
Project-URL: Source Code, https://github.com/tonkintaylor/YOUR_REPOSITORY
Project-URL: Bug Tracker, https://github.com/tonkintaylor/YOUR_REPOSITORY/issues
Project-URL: Releases, https://github.com/tonkintaylor/YOUR_REPOSITORY/releases
Project-URL: Source Archive, https://github.com/tonkintaylor/YOUR_REPOSITORY/archive/db795ca0640b55c74c65e80f134dbfebd41bfc01.zip
Author-email: Bilbo Baggins <bbaggins@tonkintaylor.co.nz>
Maintainer-email: Data + Analytics <Sub-DisciplineData+AnalyticsStaff@tonkintaylor.co.nz>
License-Expression: MIT
License-File: LICENSE
Classifier: Programming Language :: Python :: 3 :: Only
Classifier: Programming Language :: Python :: 3.10
Classifier: Programming Language :: Python :: 3.11
Classifier: Programming Language :: Python :: 3.12
Classifier: Programming Language :: Python :: 3.13
Requires-Python: >=3.10
Requires-Dist: attrs>=22.2.0
Requires-Dist: httpx<0.29.0,>=0.23.0
Requires-Dist: python-dateutil>=2.8.0
Requires-Dist: typing-extensions>=4.0.0
